ultrasnip.py
ultrasnip-0.1.1.dist-info/entry_points.txt
ultrasnip-0.1.1.dist-info/LICENSE
ultrasnip-0.1.1.dist-info/WHEEL
ultrasnip-0.1.1.dist-info/METADATA
ultrasnip-0.1.1.dist-info/RECORD
